[
  {
    "provinceId": "seoul",
    "provinceName": "Seoul",
    "overview": "Capital city with multiple masjids and halal restaurants. Popular for cultural sites like Gyeongbokgung Palace and Namsan Tower.",
    "image": "/images/provinces/seoul.avif"
  },
  {
    "provinceId": "busan",
    "provinceName": "Busan",
    "image": "/images/provinces/busan.webp",
    "overview": "Coastal city with a few mosques and halal eateries. Famous for Haeundae Beach and Jagalchi Fish Market."
  },
  {
    "provinceId": "incheon",
    "provinceName": "Incheon",
    "image": "/images/provinces/incheon.jpg",
    "overview": "Gateway city with masjids near the airport and halal-friendly spots. Known for Chinatown and Incheon Grand Park."
  },
  {
    "provinceId": "daegu",
    "provinceName": "Daegu",
    "image": "/images/provinces/daegu.jpg",
    "overview": "Has local mosques and halal food options. Attractions include Palgong Mountain and Seomun Market."
  },
  {
    "provinceId": "gwangju",
    "provinceName": "Gwangju",
    "image": "/images/provinces/gwangju.jpg",
    "overview": "Several mosques serve the Muslim community, with halal restaurants emerging. Visit the May 18 Memorial Park and Yangnim-dong."
  },
  {
    "provinceId": "daejeon",
    "provinceName": "Daejeon",
    "image": "/images/provinces/deajeon.webp",
    "overview": "Offers mosque facilities and halal eateries. Science and tech city with Expo Park and Hanbat Arboretum."
  },
  {
    "provinceId": "ulsan",
    "provinceName": "Ulsan",
    "image": "/images/provinces/ulsan.jpg",
    "overview": "Industrial city with some mosques and halal options. Popular for Taehwa River and Ulsan Grand Park."
  },
  {
    "provinceId": "sejong",
    "provinceName": "Sejong",
    "image": "/images/provinces/sejong.jpg",
    "overview": "New administrative city with growing Muslim-friendly facilities. Visit Sejong Lake Park and Government Complex."
  },
  {
    "provinceId": "jeju",
    "provinceName": "Jeju",
    "image": "/images/provinces/jeju.jpg",
    "overview": "Tourist island with halal food and prayer spaces. Known for Jeju Olle Trail and Hallasan Mountain."
  },
  {
    "provinceId": "gyeonggi-do",
    "provinceName": "Gyeonggi-do",
    "image": "/images/provinces/gyeonggi-do.avif",
    "overview": "Surrounds Seoul, many masjids and halal restaurants. Attractions include DMZ tours and Korean Folk Village."
  },
  {
    "provinceId": "gangwon-do",
    "provinceName": "Gangwon-do",
    "image": "/images/provinces/gangwon-do.jpg",
    "overview": "Mountainous province with mosques and limited halal eateries. Famous for ski resorts and Seoraksan National Park."
  },
  {
    "provinceId": "chungcheongbuk-do",
    "provinceName": "Chungcheongbuk-do",
    "image": "/images/provinces/chungcheongbuk-do.webp",
    "overview": "Central province with mosque facilities and halal food emerging. Notable sites include Danyang and Cheongwon."
  },
  {
    "provinceId": "chungcheongnam-do",
    "provinceName": "Chungcheongnam-do",
    "image": "/images/provinces/chungcheongnam-do.jpg",
    "overview": "Western province with growing Muslim community and halal options. Visit Seosan and coastal areas."
  },
  {
    "provinceId": "jeollabuk-do",
    "provinceName": "Jeollabuk-do",
    "image": "/images/provinces/jeollabuk-do.webp",
    "overview": "Known for cultural heritage and mosque presence. Halal food options increasing. Explore Jeonju Hanok Village."
  },
  {
    "provinceId": "jeollanam-do",
    "provinceName": "Jeollanam-do",
    "image": "/images/provinces/jeollanam-do.avif",
    "overview": "Southern province with mosques and halal eateries. Famous for Suncheon Bay and coastal beauty."
  },
  {
    "provinceId": "gyeongsangbuk-do",
    "provinceName": "Gyeongsangbuk-do",
    "image": "/images/provinces/gyeongsangbuk-do.jpg",
    "overview": "Has mosque facilities and halal food in cities. Popular for historical sites like Andong Hahoe Village."
  },
  {
    "provinceId": "gyeongsangnam-do",
    "provinceName": "Gyeongsangnam-do",
    "image": "/images/provinces/gyeongsangnam-do.jpg",
    "overview": "Southern coastal province with mosque and halal presence. Visit Changwon and scenic coastal spots."
  }
]
